mopeka_pro_check/__init__.py
mopeka_pro_check/advertisement.py
mopeka_pro_check/sensor.py
mopeka_pro_check/service.py
mopeka_pro_check-0.1.0.dist-info/LICENSE
mopeka_pro_check-0.1.0.dist-info/METADATA
mopeka_pro_check-0.1.0.dist-info/WHEEL
mopeka_pro_check-0.1.0.dist-info/top_level.txt
mopeka_pro_check-0.1.0.dist-info/RECORD
