Metadata-Version: 2.1
Name: mopeka-pro-check
Version: 0.1.0
Summary: A library for reading Mopeka Pro Check BLE sensors
Home-page: https://github.com/spbrogan/mopeka_pro_check
Author: Sean Brogan
Author-email: spbrogan@live.com
License: MIT
Platform: UNKNOWN
Classifier: Programming Language :: Python :: 3
Classifier: License :: OSI Approved :: MIT License
Classifier: Operating System :: OS Independent
Requires-Python: >=3.7
Requires-Dist: bleson (>=0.1.6)
